{
  "hash": "fb73b11f",
  "browserHash": "16e10f6a",
  "optimized": {
    "schemastery": {
      "src": "../../node_modules/schemastery/lib/index.mjs",
      "file": "schemastery.js",
      "fileHash": "fcff96ab",
      "needsInterop": false
    },
    "element-plus": {
      "src": "../../node_modules/element-plus/es/index.mjs",
      "file": "element-plus.js",
      "fileHash": "b111c118",
      "needsInterop": false
    },
    "@koishijs/client": {
      "src": "../../node_modules/@koishijs/client/client/index.ts",
      "file": "@koishijs_client.js",
      "fileHash": "d5c695e4",
      "needsInterop": false
    },
    "@vueuse/core": {
      "src": "../../node_modules/@vueuse/core/index.mjs",
      "file": "@vueuse_core.js",
      "fileHash": "77aa0a6c",
      "needsInterop": false
    },
    "vue": {
      "src": "../../node_modules/vue/dist/vue.runtime.esm-bundler.js",
      "file": "vue.js",
      "fileHash": "a4a2450a",
      "needsInterop": false
    },
    "vue-router": {
      "src": "../../node_modules/vue-router/dist/vue-router.mjs",
      "file": "vue-router.js",
      "fileHash": "c1117332",
      "needsInterop": false
    }
  },
  "chunks": {
    "chunk-YIT44FLZ": {
      "file": "chunk-YIT44FLZ.js"
    },
    "chunk-3MWN6O2W": {
      "file": "chunk-3MWN6O2W.js"
    },
    "chunk-NIGR53XG": {
      "file": "chunk-NIGR53XG.js"
    },
    "chunk-EKSRAS6R": {
      "file": "chunk-EKSRAS6R.js"
    },
    "chunk-2RG3FVYL": {
      "file": "chunk-2RG3FVYL.js"
    },
    "chunk-IN47U6CF": {
      "file": "chunk-IN47U6CF.js"
    }
  }
}